SparkJiqiXuexiSuanfaYanjiuHeYuanmaFenxi/README.md
SparkJiqiXuexiSuanfaYanjiuHeYuanmaFenxi/__init__.py
SparkJiqiXuexiSuanfaYanjiuHeYuanmaFenxi/__main__.py
SparkJiqiXuexiSuanfaYanjiuHeYuanmaFenxi/file.epub
SparkJiqiXuexiSuanfaYanjiuHeYuanmaFenxi/index.html
SparkJiqiXuexiSuanfaYanjiuHeYuanmaFenxi/css/__init__.py
SparkJiqiXuexiSuanfaYanjiuHeYuanmaFenxi/css/annotations.css
SparkJiqiXuexiSuanfaYanjiuHeYuanmaFenxi/css/main.css
SparkJiqiXuexiSuanfaYanjiuHeYuanmaFenxi/css/normalize.css
SparkJiqiXuexiSuanfaYanjiuHeYuanmaFenxi/css/popup.css
SparkJiqiXuexiSuanfaYanjiuHeYuanmaFenxi/font/__init__.py
SparkJiqiXuexiSuanfaYanjiuHeYuanmaFenxi/font/fontello.eot
SparkJiqiXuexiSuanfaYanjiuHeYuanmaFenxi/font/fontello.svg
SparkJiqiXuexiSuanfaYanjiuHeYuanmaFenxi/font/fontello.ttf
SparkJiqiXuexiSuanfaYanjiuHeYuanmaFenxi/font/fontello.woff
SparkJiqiXuexiSuanfaYanjiuHeYuanmaFenxi/img/__init__.py
SparkJiqiXuexiSuanfaYanjiuHeYuanmaFenxi/img/annotator-glyph-sprite.png
SparkJiqiXuexiSuanfaYanjiuHeYuanmaFenxi/img/annotator-icon-sprite.png
SparkJiqiXuexiSuanfaYanjiuHeYuanmaFenxi/img/apple-touch-icon.png
SparkJiqiXuexiSuanfaYanjiuHeYuanmaFenxi/img/cancelfullscreen.png
SparkJiqiXuexiSuanfaYanjiuHeYuanmaFenxi/img/close.png
SparkJiqiXuexiSuanfaYanjiuHeYuanmaFenxi/img/fullscreen.png
SparkJiqiXuexiSuanfaYanjiuHeYuanmaFenxi/img/loader.gif
SparkJiqiXuexiSuanfaYanjiuHeYuanmaFenxi/img/menu-icon.png
SparkJiqiXuexiSuanfaYanjiuHeYuanmaFenxi/img/save.png
SparkJiqiXuexiSuanfaYanjiuHeYuanmaFenxi/img/saved.png
SparkJiqiXuexiSuanfaYanjiuHeYuanmaFenxi/img/settings-s.png
SparkJiqiXuexiSuanfaYanjiuHeYuanmaFenxi/img/settings.png
SparkJiqiXuexiSuanfaYanjiuHeYuanmaFenxi/img/star.png
SparkJiqiXuexiSuanfaYanjiuHeYuanmaFenxi/js/__init__.py
SparkJiqiXuexiSuanfaYanjiuHeYuanmaFenxi/js/epub.js
SparkJiqiXuexiSuanfaYanjiuHeYuanmaFenxi/js/epub.min.js
SparkJiqiXuexiSuanfaYanjiuHeYuanmaFenxi/js/epub.min.map
SparkJiqiXuexiSuanfaYanjiuHeYuanmaFenxi/js/hooks.min.js
SparkJiqiXuexiSuanfaYanjiuHeYuanmaFenxi/js/hooks.min.map
spark_jiqi_xuexi_suanfa_yanjiu_he_yuanma_fenxi-2024.3.4.0.dist-info/METADATA
spark_jiqi_xuexi_suanfa_yanjiu_he_yuanma_fenxi-2024.3.4.0.dist-info/WHEEL
spark_jiqi_xuexi_suanfa_yanjiu_he_yuanma_fenxi-2024.3.4.0.dist-info/entry_points.txt
spark_jiqi_xuexi_suanfa_yanjiu_he_yuanma_fenxi-2024.3.4.0.dist-info/top_level.txt
spark_jiqi_xuexi_suanfa_yanjiu_he_yuanma_fenxi-2024.3.4.0.dist-info/RECORD
